mr.laforge-0.9-py2.7-nspkg.pth
mr/laforge/__init__.py
mr/laforge/controllerplugin.py
mr/laforge/rpcinterface.py
mr.laforge-0.9.dist-info/METADATA
mr.laforge-0.9.dist-info/RECORD
mr.laforge-0.9.dist-info/WHEEL
mr.laforge-0.9.dist-info/entry_points.txt
mr.laforge-0.9.dist-info/namespace_packages.txt
mr.laforge-0.9.dist-info/top_level.txt
mr.laforge-0.9.dist-info/zip-safe
