Metadata-Version: 2.1
Name: mr.laforge
Version: 0.9
Summary: Plugins and utilities for supervisor
Home-page: http://github.com/fschulze/mr.laforge
Author: Florian Schulze
Author-email: florian.schulze@gmx.net
License: BSD
Platform: UNKNOWN
Requires-Dist: setuptools
Requires-Dist: supervisor
